bin2fasta/.converter.cpp.cppimporthash
bin2fasta/.rendered.converter.cpp
bin2fasta/__init__.py
bin2fasta/converter.cpp
bin2fasta/crypto.py
bin2fasta/main.py
bin2fasta/tests/__init__.py
bin2fasta/tests/test_all.py
bin2fasta-0.0.2.dist-info/entry_points.txt
bin2fasta-0.0.2.dist-info/WHEEL
bin2fasta-0.0.2.dist-info/METADATA
bin2fasta-0.0.2.dist-info/RECORD
